MANIFEST.in
README.md
fastentrypoints.py
setup.cfg
setup.py
assnake/__init__.py
assnake/config_internal.ini
assnake/config_internal.py
assnake/utils.py
assnake.egg-info/PKG-INFO
assnake.egg-info/SOURCES.txt
assnake.egg-info/dependency_links.txt
assnake.egg-info/entry_points.txt
assnake.egg-info/requires.txt
assnake.egg-info/top_level.txt
assnake/api/__init__.py
assnake/api/fs_helpers.py
assnake/api/loaders.py
assnake/cli/__init__.py
assnake/cli/assnake_cli.py
assnake/cli/cli_utils.py
assnake/cli/init_config.py
assnake/cli/commands/__init__.py
assnake/cli/commands/cmd_run.py
assnake/cli/commands/commands_assembly.py
assnake/cli/commands/dataset_commands.py
assnake/cli/commands/init.py
assnake/core/__init__.py
assnake/core/dataset.py
assnake/core/pipeline.py
assnake/core/result.py
assnake/core/sample_set.py
assnake/core/snake_module.py
assnake/snake/config_template.yml
assnake/snake/snake_base.py
assnake/snake/wc_config.yaml
assnake/viz/__init__.py
assnake/viz/biodash_clustermap.py
assnake/viz/general.py